emath/__init__.py
emath/_b.hpp
emath/_bvector1.hpp
emath/_bvector2.hpp
emath/_bvector3.hpp
emath/_bvector4.hpp
emath/_d.hpp
emath/_dmatrix2x2.hpp
emath/_dmatrix2x3.hpp
emath/_dmatrix2x4.hpp
emath/_dmatrix3x2.hpp
emath/_dmatrix3x3.hpp
emath/_dmatrix3x4.hpp
emath/_dmatrix4x2.hpp
emath/_dmatrix4x3.hpp
emath/_dmatrix4x4.hpp
emath/_dquaternion.hpp
emath/_dvector1.hpp
emath/_dvector2.hpp
emath/_dvector3.hpp
emath/_dvector4.hpp
emath/_emath.cpp
emath/_emath.cpython-312-x86_64-linux-gnu.so
emath/_emath.cpython-313-x86_64-linux-gnu.so
emath/_emath.pyi
emath/_f.hpp
emath/_fmatrix2x2.hpp
emath/_fmatrix2x3.hpp
emath/_fmatrix2x4.hpp
emath/_fmatrix3x2.hpp
emath/_fmatrix3x3.hpp
emath/_fmatrix3x4.hpp
emath/_fmatrix4x2.hpp
emath/_fmatrix4x3.hpp
emath/_fmatrix4x4.hpp
emath/_fquaternion.hpp
emath/_fvector1.hpp
emath/_fvector2.hpp
emath/_fvector3.hpp
emath/_fvector4.hpp
emath/_i.hpp
emath/_i16.hpp
emath/_i16vector1.hpp
emath/_i16vector2.hpp
emath/_i16vector3.hpp
emath/_i16vector4.hpp
emath/_i32.hpp
emath/_i32vector1.hpp
emath/_i32vector2.hpp
emath/_i32vector3.hpp
emath/_i32vector4.hpp
emath/_i64.hpp
emath/_i64vector1.hpp
emath/_i64vector2.hpp
emath/_i64vector3.hpp
emath/_i64vector4.hpp
emath/_i8.hpp
emath/_i8vector1.hpp
emath/_i8vector2.hpp
emath/_i8vector3.hpp
emath/_i8vector4.hpp
emath/_ivector1.hpp
emath/_ivector2.hpp
emath/_ivector3.hpp
emath/_ivector4.hpp
emath/_matrixtype.hpp
emath/_module.hpp
emath/_modulestate.hpp
emath/_podtype.hpp
emath/_podtyping.py
emath/_pydantic.py
emath/_quaterniontype.hpp
emath/_test_api.c
emath/_test_api.cpython-312-x86_64-linux-gnu.so
emath/_test_api.cpython-313-x86_64-linux-gnu.so
emath/_type.hpp
emath/_u.hpp
emath/_u16.hpp
emath/_u16vector1.hpp
emath/_u16vector2.hpp
emath/_u16vector3.hpp
emath/_u16vector4.hpp
emath/_u32.hpp
emath/_u32vector1.hpp
emath/_u32vector2.hpp
emath/_u32vector3.hpp
emath/_u32vector4.hpp
emath/_u64.hpp
emath/_u64vector1.hpp
emath-0.9.0.dist-info/METADATA
emath-0.9.0.dist-info/WHEEL
emath-0.9.0.dist-info/RECORD
