Metadata-Version: 2.4
Name: emath
Version: 0.9.0
Summary: Fast immutable math primitives.
Author: Erik Soma
Author-email: stillusingirc@gmail.com
Requires-Python: >=3.12
Classifier: Programming Language :: Python :: 3
Classifier: Programming Language :: Python :: 3.12
Classifier: Programming Language :: Python :: 3.13
Classifier: Programming Language :: Python :: 3.14
